bg_mpl_stylesheets/__init__.py
bg_mpl_stylesheets/bg_mpl_stylesheet
bg_mpl_stylesheets/colors.py
bg_mpl_stylesheets/inkscape_tools.py
bg_mpl_stylesheets/styles.py
bg_mpl_stylesheets/translate.py
bg_mpl_stylesheets/version.py
bg_mpl_stylesheets-0.5.1.dist-info/AUTHORS.rst
bg_mpl_stylesheets-0.5.1.dist-info/LICENSE.rst
bg_mpl_stylesheets-0.5.1.dist-info/METADATA
bg_mpl_stylesheets-0.5.1.dist-info/WHEEL
bg_mpl_stylesheets-0.5.1.dist-info/top_level.txt
bg_mpl_stylesheets-0.5.1.dist-info/RECORD
